validus/__init__.py
validus/isbn.py
validus/phones.py
validus/utils.py
validus/validators.py
validus-0.3.0.dist-info/DESCRIPTION.rst
validus-0.3.0.dist-info/METADATA
validus-0.3.0.dist-info/RECORD
validus-0.3.0.dist-info/WHEEL
validus-0.3.0.dist-info/metadata.json
validus-0.3.0.dist-info/top_level.txt
