Metadata-Version: 1.1
Name: validus
Version: 0.3.0
Summary: A dead simple Python string validation library.
Home-page: https://github.com/shopnilsazal/validus
Author: Rafiqul Hasan
Author-email: shopnilsazal@gmail.com
License: BSD license
Keywords: validus
Platform: UNKNOWN
Classifier: Development Status :: 2 - Pre-Alpha
Classifier: Intended Audience :: Developers
Classifier: License :: OSI Approved :: BSD License
Classifier: Natural Language :: English
Classifier: Programming Language :: Python :: 3
Classifier: Programming Language :: Python :: 3.3
Classifier: Programming Language :: Python :: 3.4
Classifier: Programming Language :: Python :: 3.5
Classifier: Programming Language :: Python :: 3.6
